lakehouse_engine/__init__.py
lakehouse_engine/engine.py
lakehouse_engine/algorithms/__init__.py
lakehouse_engine/algorithms/algorithm.py
lakehouse_engine/algorithms/data_loader.py
lakehouse_engine/algorithms/dq_validator.py
lakehouse_engine/algorithms/exceptions.py
lakehouse_engine/algorithms/gab.py
lakehouse_engine/algorithms/reconciliator.py
lakehouse_engine/algorithms/sensor.py
lakehouse_engine/algorithms/sensors/__init__.py
lakehouse_engine/algorithms/sensors/heartbeat.py
lakehouse_engine/algorithms/sensors/sensor.py
lakehouse_engine/configs/__init__.py
lakehouse_engine/configs/engine.yaml
lakehouse_engine/core/__init__.py
lakehouse_engine/core/dbfs_file_manager.py
lakehouse_engine/core/definitions.py
lakehouse_engine/core/exec_env.py
lakehouse_engine/core/executable.py
lakehouse_engine/core/file_manager.py
lakehouse_engine/core/gab_manager.py
lakehouse_engine/core/gab_sql_generator.py
lakehouse_engine/core/s3_file_manager.py
lakehouse_engine/core/sensor_manager.py
lakehouse_engine/core/table_manager.py
lakehouse_engine/dq_processors/__init__.py
lakehouse_engine/dq_processors/dq_factory.py
lakehouse_engine/dq_processors/exceptions.py
lakehouse_engine/dq_processors/validator.py
lakehouse_engine/dq_processors/custom_expectations/__init__.py
lakehouse_engine/dq_processors/custom_expectations/expect_column_pair_a_to_be_not_equal_to_b.py
lakehouse_engine/dq_processors/custom_expectations/expect_column_pair_a_to_be_smaller_or_equal_than_b.py
lakehouse_engine/dq_processors/custom_expectations/expect_column_pair_date_a_to_be_greater_than_or_equal_to_date_b.py
lakehouse_engine/dq_processors/custom_expectations/expect_column_values_to_be_date_not_older_than.py
lakehouse_engine/dq_processors/custom_expectations/expect_column_values_to_not_be_null_or_empty_string.py
lakehouse_engine/dq_processors/custom_expectations/expect_multicolumn_column_a_must_equal_b_or_c.py
lakehouse_engine/dq_processors/custom_expectations/expect_queried_column_agg_value_to_be.py
lakehouse_engine-1.27.1.dist-info/LICENSE.txt
lakehouse_engine-1.27.1.dist-info/METADATA
lakehouse_engine-1.27.1.dist-info/WHEEL
lakehouse_engine-1.27.1.dist-info/top_level.txt
lakehouse_engine-1.27.1.dist-info/RECORD
