Metadata-Version: 2.1
Name: lakehouse-engine
Version: 1.27.1
Summary: A configuration-driven Spark framework serving as the engine for several lakehouse algorithms and data flows.
Author-email: Adidas Lakehouse Foundations Team <software.engineering@adidas.com>
License: Apache License
Project-URL: Repository, https://github.com/adidas/lakehouse-engine
Project-URL: Documentation, https://adidas.github.io/lakehouse-engine-docs/index.html
Project-URL: Issues, https://github.com/adidas/lakehouse-engine/issues
Project-URL: Releases, https://github.com/adidas/lakehouse-engine/releases
Keywords: framework,big-data,spark,databricks,data-quality,data-engineering,great-expectations,lakehouse,delta-lake,configuration-driver
Classifier: Development Status :: 5 - Production/Stable
Classifier: Programming Language :: Python :: 3
Classifier: Intended Audience :: Developers
Classifier: Intended Audience :: Science/Research
Classifier: Intended Audience :: Other Audience
Classifier: Operating System :: OS Independent
Classifier: Topic :: Scientific/Engineering
Classifier: Topic :: Software Development
Classifier: License :: OSI Approved :: Apache Software License
Requires-Python: >=3.12
License-File: LICENSE.txt
Requires-Dist: boto3 ==1.40.23
Requires-Dist: botocore ==1.40.23
Requires-Dist: jinja2 ==3.1.6
Requires-Dist: jmespath ==1.0.1
Requires-Dist: markupsafe ==3.0.2
Requires-Dist: pendulum ==3.0.0
Requires-Dist: python-dateutil ==2.9.0.post0
Requires-Dist: pyyaml ==6.0.1
Requires-Dist: s3transfer ==0.13.1
Requires-Dist: six ==1.17.0
Requires-Dist: time-machine ==2.19.0
Requires-Dist: tzdata ==2025.2
Requires-Dist: urllib3 ==2.5.0
Provides-Extra: azure
Requires-Dist: aiohappyeyeballs ==2.6.1 ; extra == 'azure'
Requires-Dist: aiohttp ==3.12.14 ; extra == 'azure'
Requires-Dist: aiosignal ==1.4.0 ; extra == 'azure'
Requires-Dist: anyio ==4.9.0 ; extra == 'azure'
Requires-Dist: attrs ==25.3.0 ; extra == 'azure'
Requires-Dist: azure-core ==1.34.0 ; extra == 'azure'
Requires-Dist: azure-identity ==1.23.0 ; extra == 'azure'
Requires-Dist: certifi ==2025.4.26 ; extra == 'azure'
Requires-Dist: cffi ==1.17.1 ; extra == 'azure'
Requires-Dist: charset-normalizer ==3.4.2 ; extra == 'azure'
Requires-Dist: cryptography ==45.0.3 ; extra == 'azure'
Requires-Dist: frozenlist ==1.6.2 ; extra == 'azure'
Requires-Dist: h11 ==0.16.0 ; extra == 'azure'
Requires-Dist: h2 ==4.3.0 ; extra == 'azure'
Requires-Dist: hpack ==4.1.0 ; extra == 'azure'
Requires-Dist: httpcore ==1.0.9 ; extra == 'azure'
Requires-Dist: httpx[http2] ==0.28.1 ; extra == 'azure'
Requires-Dist: hyperframe ==6.1.0 ; extra == 'azure'
Requires-Dist: idna ==3.10 ; extra == 'azure'
Requires-Dist: importlib-metadata ==8.7.0 ; extra == 'azure'
Requires-Dist: microsoft-kiota-abstractions ==1.9.3 ; extra == 'azure'
Requires-Dist: microsoft-kiota-authentication-azure ==1.9.3 ; extra == 'azure'
Requires-Dist: microsoft-kiota-http ==1.9.3 ; extra == 'azure'
Requires-Dist: microsoft-kiota-serialization-form ==1.9.3 ; extra == 'azure'
Requires-Dist: microsoft-kiota-serialization-json ==1.9.3 ; extra == 'azure'
Requires-Dist: microsoft-kiota-serialization-multipart ==1.9.3 ; extra == 'azure'
Requires-Dist: microsoft-kiota-serialization-text ==1.9.3 ; extra == 'azure'
Requires-Dist: msal ==1.33.0 ; extra == 'azure'
Requires-Dist: msal-extensions ==1.3.1 ; extra == 'azure'
Requires-Dist: msgraph-core ==1.3.4 ; extra == 'azure'
Requires-Dist: msgraph-sdk ==1.40.0 ; extra == 'azure'
Requires-Dist: multidict ==6.4.4 ; extra == 'azure'
Requires-Dist: nest-asyncio ==1.6.0 ; extra == 'azure'
Requires-Dist: opentelemetry-api ==1.34.0 ; extra == 'azure'
Requires-Dist: opentelemetry-sdk ==1.34.0 ; extra == 'azure'
Requires-Dist: opentelemetry-semantic-conventions ==0.55b0 ; extra == 'azure'
Requires-Dist: propcache ==0.3.1 ; extra == 'azure'
Requires-Dist: pycparser ==2.22 ; extra == 'azure'
Requires-Dist: pyjwt[crypto] ==2.10.1 ; extra == 'azure'
Requires-Dist: requests ==2.32.4 ; extra == 'azure'
Requires-Dist: six ==1.17.0 ; extra == 'azure'
Requires-Dist: sniffio ==1.3.1 ; extra == 'azure'
Requires-Dist: std-uritemplate ==2.0.5 ; extra == 'azure'
Requires-Dist: typing-extensions ==4.14.0 ; extra == 'azure'
Requires-Dist: urllib3 ==2.5.0 ; extra == 'azure'
Requires-Dist: yarl ==1.20.0 ; extra == 'azure'
Requires-Dist: zipp ==3.22.0 ; extra == 'azure'
Provides-Extra: dq
Requires-Dist: altair ==4.2.2 ; extra == 'dq'
Requires-Dist: annotated-types ==0.7.0 ; extra == 'dq'
Requires-Dist: attrs ==25.3.0 ; extra == 'dq'
Requires-Dist: backoff ==2.2.1 ; extra == 'dq'
Requires-Dist: certifi ==2025.4.26 ; extra == 'dq'
Requires-Dist: cffi ==1.17.1 ; extra == 'dq'
Requires-Dist: charset-normalizer ==3.4.2 ; extra == 'dq'
Requires-Dist: cryptography ==45.0.3 ; extra == 'dq'
Requires-Dist: distro ==1.9.0 ; extra == 'dq'
Requires-Dist: entrypoints ==0.4 ; extra == 'dq'
Requires-Dist: great-expectations ==1.5.11 ; extra == 'dq'
Requires-Dist: idna ==3.10 ; extra == 'dq'
Requires-Dist: jinja2 ==3.1.6 ; extra == 'dq'
Requires-Dist: jsonschema ==4.24.0 ; extra == 'dq'
Requires-Dist: jsonschema-specifications ==2025.4.1 ; extra == 'dq'
Requires-Dist: markupsafe ==3.0.2 ; extra == 'dq'
Requires-Dist: marshmallow ==3.26.1 ; extra == 'dq'
Requires-Dist: mistune ==3.1.3 ; extra == 'dq'
Requires-Dist: monotonic ==1.6 ; extra == 'dq'
Requires-Dist: numpy ==1.26.4 ; extra == 'dq'
Requires-Dist: packaging ==25.0 ; extra == 'dq'
Requires-Dist: pandas ==2.1.4 ; extra == 'dq'
Requires-Dist: posthog ==3.25.0 ; extra == 'dq'
Requires-Dist: pycparser ==2.22 ; extra == 'dq'
Requires-Dist: pydantic ==2.11.5 ; extra == 'dq'
Requires-Dist: pydantic-core ==2.33.2 ; extra == 'dq'
Requires-Dist: pyparsing ==3.2.3 ; extra == 'dq'
Requires-Dist: python-dateutil ==2.9.0.post0 ; extra == 'dq'
Requires-Dist: pytz ==2025.2 ; extra == 'dq'
Requires-Dist: referencing ==0.36.2 ; extra == 'dq'
Requires-Dist: requests ==2.32.4 ; extra == 'dq'
Requires-Dist: rpds-py ==0.25.1 ; extra == 'dq'
Requires-Dist: ruamel-yaml ==0.18.13 ; extra == 'dq'
Requires-Dist: ruamel-yaml-clib ==0.2.12 ; extra == 'dq'
Requires-Dist: scipy ==1.15.3 ; extra == 'dq'
Requires-Dist: six ==1.17.0 ; extra == 'dq'
Requires-Dist: toolz ==1.0.0 ; extra == 'dq'
Requires-Dist: tqdm ==4.67.1 ; extra == 'dq'
Requires-Dist: typing-extensions ==4.14.0 ; extra == 'dq'
Requires-Dist: typing-inspection ==0.4.1 ; extra == 'dq'
Requires-Dist: tzdata ==2025.2 ; extra == 'dq'
Requires-Dist: tzlocal ==5.3.1 ; extra == 'dq'
Requires-Dist: urllib3 ==2.5.0 ; extra == 'dq'
Provides-Extra: os
Requires-Dist: delta-spark ==3.3.1 ; extra == 'os'
Requires-Dist: importlib-metadata ==8.7.0 ; extra == 'os'
Requires-Dist: py4j ==0.10.9.7 ; extra == 'os'
Requires-Dist: pyspark ==3.5.5 ; extra == 'os'
Requires-Dist: zipp ==3.22.0 ; extra == 'os'
Provides-Extra: sftp
Requires-Dist: bcrypt ==4.3.0 ; extra == 'sftp'
Requires-Dist: cffi ==1.17.1 ; extra == 'sftp'
Requires-Dist: cryptography ==45.0.3 ; extra == 'sftp'
Requires-Dist: invoke ==2.2.0 ; extra == 'sftp'
Requires-Dist: paramiko ==4.0.0 ; extra == 'sftp'
Requires-Dist: pycparser ==2.22 ; extra == 'sftp'
Requires-Dist: pynacl ==1.5.0 ; extra == 'sftp'
Provides-Extra: sharepoint
Requires-Dist: certifi ==2025.4.26 ; extra == 'sharepoint'
Requires-Dist: cffi ==1.17.1 ; extra == 'sharepoint'
Requires-Dist: charset-normalizer ==3.4.2 ; extra == 'sharepoint'
Requires-Dist: cryptography ==45.0.3 ; extra == 'sharepoint'
Requires-Dist: idna ==3.10 ; extra == 'sharepoint'
Requires-Dist: msal ==1.33.0 ; extra == 'sharepoint'
Requires-Dist: pycparser ==2.22 ; extra == 'sharepoint'
Requires-Dist: pyjwt[crypto] ==2.10.1 ; extra == 'sharepoint'
Requires-Dist: requests ==2.32.4 ; extra == 'sharepoint'
Requires-Dist: tenacity ==9.0.0 ; extra == 'sharepoint'
Requires-Dist: urllib3 ==2.5.0 ; extra == 'sharepoint'
